musion/__init__.py
musion/beat/__init__.py
musion/beat/inference.py
musion/beat/postprocessor.py
musion/beat/utils.py
musion/dev_tools/__init__.py
musion/dev_tools/dev_tools.py
musion/separate/__init__.py
musion/separate/inference.py
musion/separate/utils.py
musion/struct/__init__.py
musion/struct/inference.py
musion/transcribe/__init__.py
musion/transcribe/inference.py
musion/transcribe/regression.py
musion/utils/__init__.py
musion/utils/base.py
musion/utils/cli.py
musion/utils/distributed.py
musion/utils/dynamic_gpu_parallel.py
musion/utils/ort_musion_base.py
musion/utils/parallel.py
musion/utils/pickableort.py
musion/utils/pkg_util.py
musion/utils/tools.py
musion-0.3.1.dist-info/LICENSE
musion-0.3.1.dist-info/METADATA
musion-0.3.1.dist-info/WHEEL
musion-0.3.1.dist-info/entry_points.txt
musion-0.3.1.dist-info/top_level.txt
musion-0.3.1.dist-info/RECORD
