Metadata-Version: 2.2
Name: musion
Version: 0.3.1
Summary: MUSION, a toolbox for music information retrieval and music signal processing.
Home-page: https://github.com/zhaotw/musion
Author: zhaotw
Author-email: zhao_tw@outlook.com
License: MIT
Platform: UNKNOWN
Classifier: License :: OSI Approved :: MIT License
Classifier: Operating System :: OS Independent
Classifier: Topic :: Multimedia :: Sound/Audio :: Analysis
Classifier: Topic :: Scientific/Engineering :: Artificial Intelligence
Classifier: Programming Language :: Python :: 3
License-File: LICENSE
Requires-Dist: einops>=0.7.0
Requires-Dist: tqdm
Requires-Dist: mido
Requires-Dist: numpy>=1.22.4
Requires-Dist: torchaudio>=0.11.0
Requires-Dist: onnxruntime-gpu>=1.11.0
Provides-Extra: test
Requires-Dist: pytest>=6.1.1; extra == "test"
Provides-Extra: dev
Requires-Dist: tf2onnx; extra == "dev"
Requires-Dist: pylint; extra == "dev"
